notirss.py
notirss-0.1.0.dist-info/LICENSE
notirss-0.1.0.dist-info/METADATA
notirss-0.1.0.dist-info/WHEEL
notirss-0.1.0.dist-info/entry_points.txt
notirss-0.1.0.dist-info/top_level.txt
notirss-0.1.0.dist-info/RECORD
