Metadata-Version: 2.1
Name: notirss
Version: 0.1.0
Summary: Simple CLI RSS real-time notifier via webhook.
Home-page: UNKNOWN
Author: Ivan Gonzalez
Author-email: alo@ivgo.me
License: UNKNOWN
Platform: UNKNOWN
Requires-Python: >=3.6
Requires-Dist: feedparser
Requires-Dist: requests
